README.md
pyproject.toml
setup.py
cassandra_orm.egg-info/PKG-INFO
cassandra_orm.egg-info/SOURCES.txt
cassandra_orm.egg-info/dependency_links.txt
cassandra_orm.egg-info/entry_points.txt
cassandra_orm.egg-info/not-zip-safe
cassandra_orm.egg-info/requires.txt
cassandra_orm.egg-info/top_level.txt
corm/__init__.py
corm/annotations.py
corm/auth.py
corm/constants.py
corm/datatypes.py
corm/encoders.py
corm/models.py
corm/utils.py
corm/etl/__init__.py
corm/etl/constants.py
corm/etl/datatypes.py
corm/etl/factory.py
corm/etl/helpers.py
corm/etl/utils.py
corm/etl/factory_testing/__init__.py
corm/etl/factory_testing/models.py
corm/etl/factory_testing/utils.py