Metadata-Version: 2.1
Name: cassandra-orm
Version: 0.0.15
Summary: Cassandra ORM which uses Python annotations simular to the typing.NamedTuple API
Home-page: https://github.com/jbcurtin/cassandra-orm
Author: Joseph Curtin <42@jbcurtin.io
Author-email: cassandra-orm@jbcurtin.io
License: MIT
Platform: UNKNOWN
Classifier: Operating System :: OS Independent
Classifier: Programming Language :: Python
Classifier: Programming Language :: Python :: 3
Classifier: Programming Language :: Python :: 3.6
Classifier: Programming Language :: Python :: 3.7
Classifier: Programming Language :: Python :: 3 :: Only
Requires-Python: >=3.7
